hayesface/HayesFace.py
hayesface/__init__.py
hayesface/commons/__init__.py
hayesface/commons/postprocess.py
hayesface/commons/preprocess.py
hayesface/model/__init__.py
hayesface/model/retinaface_model.py
hayes_face-0.0.4.dist-info/LICENSE
hayes_face-0.0.4.dist-info/METADATA
hayes_face-0.0.4.dist-info/WHEEL
hayes_face-0.0.4.dist-info/top_level.txt
hayes_face-0.0.4.dist-info/RECORD
